SidraCoreApiPythonClient/__init__.py
SidraCoreApiPythonClient/api_client.py
SidraCoreApiPythonClient/configuration.py
SidraCoreApiPythonClient/rest.py
SidraCoreApiPythonClient/api/__init__.py
SidraCoreApiPythonClient/api/apps_registry_app_api.py
SidraCoreApiPythonClient/api/assets_assets_api.py
SidraCoreApiPythonClient/api/data_factory_activity_templates_activity_templates_api.py
SidraCoreApiPythonClient/api/data_factory_data_factories_data_factories_api.py
SidraCoreApiPythonClient/api/data_factory_data_set_template_pipeline_templates_data_set_template_pipeline_template_api.py
SidraCoreApiPythonClient/api/data_factory_data_set_templates_data_set_templates_api.py
SidraCoreApiPythonClient/api/data_factory_data_source_template_pipeline_templates_data_source_template_pipeline_template_api.py
SidraCoreApiPythonClient/api/data_factory_data_source_templates_data_source_template_api.py
SidraCoreApiPythonClient/api/data_factory_data_sources_data_source_api.py
SidraCoreApiPythonClient/api/data_factory_metric_logs_data_factory_metric_logs_api.py
SidraCoreApiPythonClient/api/data_factory_pipeline_templates_pipeline_templates_api.py
SidraCoreApiPythonClient/api/data_factory_pipelines_pipelines_api.py
SidraCoreApiPythonClient/api/data_factory_trigger_templates_trigger_templates_api.py
SidraCoreApiPythonClient/api/data_factory_triggers_triggers_api.py
SidraCoreApiPythonClient/api/data_preview_data_preview_api.py
SidraCoreApiPythonClient/api/data_storage_unit_cluster_types_cluster_types_api.py
SidraCoreApiPythonClient/api/data_storage_unit_data_storage_units_data_storage_units_api.py
SidraCoreApiPythonClient/api/data_storage_unit_databricks_databricks_api.py
SidraCoreApiPythonClient/api/data_storage_unit_landing_zones_landing_zones_api.py
SidraCoreApiPythonClient/api/data_storage_unit_search_services_search_services_api.py
SidraCoreApiPythonClient/api/data_storage_unit_storage_roles_storage_roles_api.py
SidraCoreApiPythonClient/api/data_storage_unit_storages_storages_api.py
SidraCoreApiPythonClient-2025.5.5.dist-info/METADATA
SidraCoreApiPythonClient-2025.5.5.dist-info/WHEEL
SidraCoreApiPythonClient-2025.5.5.dist-info/top_level.txt
SidraCoreApiPythonClient-2025.5.5.dist-info/RECORD
