Metadata-Version: 2.1
Name: SidraCoreApiPythonClient
Version: 2025.5.5
Summary: Sidra API
Home-page: 
Author-email: info@sidra.dev
Keywords: Swagger,Sidra API
Requires-Dist: certifi
Requires-Dist: python-dateutil
Requires-Dist: six >=1.10
Requires-Dist: urllib3 >=1.15
